mkdocs_mermaid_to_svg/__init__.py
mkdocs_mermaid_to_svg/_version.py
mkdocs_mermaid_to_svg/beautiful_mermaid_runner.mjs
mkdocs_mermaid_to_svg/config.py
mkdocs_mermaid_to_svg/exceptions.py
mkdocs_mermaid_to_svg/image_generator.py
mkdocs_mermaid_to_svg/logging_config.py
mkdocs_mermaid_to_svg/markdown_processor.py
mkdocs_mermaid_to_svg/mermaid_block.py
mkdocs_mermaid_to_svg/plugin.py
mkdocs_mermaid_to_svg/processor.py
mkdocs_mermaid_to_svg/types.py
mkdocs_mermaid_to_svg/utils.py
mkdocs_mermaid_to_svg-1.2.2.dist-info/METADATA
mkdocs_mermaid_to_svg-1.2.2.dist-info/WHEEL
mkdocs_mermaid_to_svg-1.2.2.dist-info/entry_points.txt
mkdocs_mermaid_to_svg-1.2.2.dist-info/licenses/LICENSE
mkdocs_mermaid_to_svg-1.2.2.dist-info/RECORD
