Metadata-Version: 2.4
Name: mkdocs-mermaid-to-svg
Version: 1.2.2
Summary: MkDocs plugin to preprocess Mermaid diagrams into static SVG images
Project-URL: Homepage, https://github.com/nuitsjp/mkdocs-mermaid-to-svg
Project-URL: Bug Reports, https://github.com/nuitsjp/mkdocs-mermaid-to-svg/issues
Project-URL: Source, https://github.com/nuitsjp/mkdocs-mermaid-to-svg
Author: nuitsjp
License: MIT
License-File: LICENSE
Keywords: diagram,mermaid,mkdocs,preprocessing,static-generation,svg
Classifier: Development Status :: 4 - Beta
Classifier: Intended Audience :: Developers
Classifier: License :: OSI Approved :: MIT License
Classifier: Programming Language :: Python :: 3
Classifier: Programming Language :: Python :: 3.9
Classifier: Programming Language :: Python :: 3.10
Classifier: Programming Language :: Python :: 3.11
Classifier: Programming Language :: Python :: 3.12
Classifier: Topic :: Documentation
Classifier: Topic :: Text Processing :: Markup
Requires-Python: >=3.9
Requires-Dist: mkdocs>=1.4.0
